{
    "news": [
        {
            "title": "TARGET Basic Store",
        "text": "Es un programa que busca asegurar una cartera basica de productos de UNG, Vinos y Ady en el PDV.\nSe encuentra dentro de los targets anuales y su forma de medicion es bimensual. Los productos necesarios para completar el Basic Store son....\n*ENEMIGO PEPSI: Pepsi Regular familiar sin reco\n*7up familiares\n*Mirinda\n*Gatorade\n*Gaseosas SS (si es Kiosco)\n*Gaseosas Familiares Non Sugar (si es Tradicional)\n*Vino Novecento Core\n*Vino Premium o Espumante o Gin o Sidra",
            "link1": {
                "name": "Seguimiento",
                "link": "https://drive.google.com/drive/folders/1p9pnIQw1a-bT0DA9rSy7WGvRJCeilj6w"
            }
        },
        {
            "title": "TARGET B2O",
            "text": "Es un programa que busca trasladar al cliente final descuentos agresivos en productos de todos los negocios.\nEl cliente accede a la promo escaneando un QR y el pdv valida un cod para recibir puntos a cambio.\nEs target mensual de la compañia y hay objetivos por promotor de manera mensual. Para cumplir con el obj el Pdv debe canjear al menos 5 promos en el mes",
            "link1": {
                "name": "Link para canjes",
                "link": "https://bees.canjeapromo.com.ar/"
            },
            "link2": {
                "name": "Seguimiento",
                "image": "assets/images/foto-target-B20.jpg"
            }
        },
        {
            "title": "TARGET CCC MKP",
            "text": "Esta dentro de los Targets anuales, hay objetivos mensuales aperturados por promotor y se busca mediante combos y dinamicas a lo largo del mes llegar al 100%. Todos los meses hay un dia de descuentos especiales",
            "link2": {
                "name": "Seguimiento",
                "image": "assets/images/foto ccc mkp.jpg"
            }
        },
        {
            "title": "TARGET CCC Innovaciones",
            "text": "Esta dentro de los Targets anuales, hay objetivos mensuales aperturados por promotor y se busca mediante combos y dinamicas a lo largo del mes llegar al 100%. Todos los meses hay un dia de descuentos especiales.\nLos productos que aplican como Innovaciones son...\n*Brahma Dorada\n*Quilmes 0.0\n*Andes Origen Fresquita\n*Stella Blanche\n*Michelob\n*Corona 410",
            "link1": {
                "name": "Seguimiento",
                "image": "assets/images/foto-ccc-inno.jpg"
            }
        },
        {
            "title": "Proyecto 'Sacale Jugo'",
            "text": "Se trata de un proyecto que busca dar un foco especial al mercado de jugos, a partir de un analisis de las competencias y de los valores agregados de nuestras marcas se plantearon ciertos objetivos de aumento de Volumen y CCC.\nSACALE JUGO se implemento por primera vez en Abril en 3 territorios de una de las mesas del K+T de la Directa de Cordoba, debido a los excelentes resultados se extendio el proyecto a todo el OFF TRADE desde la 2ª quincena de Abril.\n\nActualmente el proyecto renueva esfuerzos en Mayo, con la inclusion de tareas en Bees Force en PDVs aplicables a ciertos criterios y con la extension al canal del ON PREMISE. ",
            "link1": {
                "name": "Presentacion del Proyecto",
                "link": "https://docs.google.com/presentation/d/1Z9A70Z_UMChfimkGOd7_1gotG4N_TvF8/edit?usp=drivesdk&ouid=117187957927752788403&rtpof=true&sd=true"
            },
            "link2": {
                "name": "Seguimiento",
                "image": "assets/images/foto-target-B20.jpg"
            }
        },
        {
            "title": "Target CCC MKP",
            "text": "Esta dentro de los Targets anuales, hay objetivos mensuales aperturados por promotor y se busca mediante combos y dinamicas a lo largo del mes llegar al 100%. Todos los meses hay un dia de descuentos especiales",
            "link1": {
                "name": "Link Marketplace day",
                "link": "https://bees.canjeapromo.com.ar/"
            },
            "link2": {
                "name": "Seguimiento",
                "link": "https://bees.canjeapromo.com.ar/"
            }
        }
    ]
}